inmanage.py
inmanage_sdk/__init__.py
inmanage_sdk/command/IpmiFunc.py
inmanage_sdk/command/RedfishFunc.py
inmanage_sdk/command/RedfishUrl.yml
inmanage_sdk/command/RestFunc.py
inmanage_sdk/command/__init__.py
inmanage_sdk/command/backup.py
inmanage_sdk/command/restore.py
inmanage_sdk/command/M5Log/__init__.py
inmanage_sdk/command/M5Log/biosPostEventStr.py
inmanage_sdk/command/M5Log/commonInfoStr.py
inmanage_sdk/command/M5Log/eventLogString.py
inmanage_sdk/command/M5Log/inspectionFilter.yml
inmanage_sdk/command/M5Log/sensorEventStr.py
inmanage_sdk/command/M5Log/sensorSpecificEventStr.py
inmanage_sdk/command/M5Log/showSensorDesc.py
inmanage_sdk/command/bios/A7.xml
inmanage_sdk/command/bios/M4.xml
inmanage_sdk/command/bios/M5.xml
inmanage_sdk/command/bios/M6-N.xml
inmanage_sdk/command/bios/M6.xml
inmanage_sdk/command/bios/M7.xml
inmanage_sdk/command/bios/M7_5.10.00.xml
inmanage_sdk/command/bios/M8.xml
inmanage_sdk/command/bios/NF3180A6.xml
inmanage_sdk/command/bios/NF3280A6.xml
inmanage_sdk/command/bios/NF5180M5.xml
inmanage_sdk/command/bios/NF5280M5.xml
inmanage_sdk/command/bios/NF5468A5.xml
inmanage_sdk/command/bios/NF5468A8.xml
inmanage_sdk/command/bios/NF5488A5.xml
inmanage_sdk/command/bios/SA5112M5.xml
inmanage_sdk/command/bios/SA5212M5.xml
inmanage_sdk/interface/Base.py
inmanage_sdk/interface/CommonA5.py
inmanage_sdk/interface/CommonA6.py
inmanage_sdk/interface/CommonA7.py
inmanage_sdk/interface/CommonA7_11308.py
inmanage_sdk/interface/CommonM5.py
inmanage_sdk/interface/CommonM6.py
inmanage_sdk/interface/CommonM6_41401.py
inmanage_sdk/interface/CommonM6_4140a.py
inmanage_sdk/interface/CommonM7.py
inmanage_sdk/interface/CommonM7_13505.py
inmanage_sdk/interface/CommonM8.py
inmanage_sdk/interface/I24M6.py
inmanage_sdk/interface/IBase.py
inmanage_sdk/interface/NF3290A8.py
inmanage_sdk/interface/NF3290M8.py
inmanage_sdk/interface/NF5180M5.py
inmanage_sdk/interface/NF5180M5Impl.py
inmanage_sdk/interface/NF5280M5.py
inmanage_sdk/interface/NF5280M5Impl.py
inmanage-1.4.4.dist-info/LICENSE
inmanage-1.4.4.dist-info/METADATA
inmanage-1.4.4.dist-info/WHEEL
inmanage-1.4.4.dist-info/top_level.txt
inmanage-1.4.4.dist-info/RECORD
