Metadata-Version: 2.1
Name: inmanage
Version: 1.4.4
Summary: ieisystem server manager api
Home-page: https://github.com/ieisystem/inManage
Author: Wangbaoshan
Author-email: wangbaoshan@ieisystem.com
License: Expat License
Classifier: Programming Language :: Python
Classifier: Programming Language :: Python :: 3
Classifier: Programming Language :: Python :: 3.4
Classifier: Programming Language :: Python :: 3.5
Classifier: Programming Language :: Python :: 3.6
Classifier: Programming Language :: Python :: 3.7
Classifier: Programming Language :: Python :: 3.8
License-File: LICENSE
Requires-Dist: pycryptodome (>=3.5.0)
Requires-Dist: PyYAML
Requires-Dist: requests (>=2.9.1)
Requires-Dist: Jpype1
Requires-Dist: requests-toolbelt
